odoo/addons/fieldservice/README.rst
odoo/addons/fieldservice/__init__.py
odoo/addons/fieldservice/__manifest__.py
odoo/addons/fieldservice/data/fsm_stage.xml
odoo/addons/fieldservice/data/fsm_team.xml
odoo/addons/fieldservice/data/ir_sequence.xml
odoo/addons/fieldservice/data/mail_message_subtype.xml
odoo/addons/fieldservice/data/module_category.xml
odoo/addons/fieldservice/demo/fsm_demo.xml
odoo/addons/fieldservice/demo/fsm_equipment.xml
odoo/addons/fieldservice/demo/fsm_location.xml
odoo/addons/fieldservice/demo/fsm_person.xml
odoo/addons/fieldservice/i18n/de.po
odoo/addons/fieldservice/i18n/es.po
odoo/addons/fieldservice/i18n/es_AR.po
odoo/addons/fieldservice/i18n/es_CL.po
odoo/addons/fieldservice/i18n/fieldservice.pot
odoo/addons/fieldservice/i18n/fr.po
odoo/addons/fieldservice/i18n/it.po
odoo/addons/fieldservice/i18n/pt.po
odoo/addons/fieldservice/i18n/pt_BR.po
odoo/addons/fieldservice/i18n/pt_PT.po
odoo/addons/fieldservice/i18n/sk.po
odoo/addons/fieldservice/models/__init__.py
odoo/addons/fieldservice/models/fsm_branch.py
odoo/addons/fieldservice/models/fsm_category.py
odoo/addons/fieldservice/models/fsm_district.py
odoo/addons/fieldservice/models/fsm_equipment.py
odoo/addons/fieldservice/models/fsm_location.py
odoo/addons/fieldservice/models/fsm_location_person.py
odoo/addons/fieldservice/models/fsm_order.py
odoo/addons/fieldservice/models/fsm_order_type.py
odoo/addons/fieldservice/models/fsm_person.py
odoo/addons/fieldservice/models/fsm_person_calendar_filter.py
odoo/addons/fieldservice/models/fsm_region.py
odoo/addons/fieldservice/models/fsm_stage.py
odoo/addons/fieldservice/models/fsm_tag.py
odoo/addons/fieldservice/models/fsm_team.py
odoo/addons/fieldservice/models/fsm_template.py
odoo/addons/fieldservice/models/fsm_territory.py
odoo/addons/fieldservice/models/res_company.py
odoo/addons/fieldservice/models/res_config_settings.py
odoo/addons/fieldservice/models/res_country.py
odoo/addons/fieldservice/models/res_partner.py
odoo12_addon_fieldservice-12.0.2.21.1.dist-info/METADATA
odoo12_addon_fieldservice-12.0.2.21.1.dist-info/WHEEL
odoo12_addon_fieldservice-12.0.2.21.1.dist-info/top_level.txt
odoo12_addon_fieldservice-12.0.2.21.1.dist-info/RECORD
