Metadata-Version: 2.1
Name: odoo12-addon-fieldservice
Version: 12.0.2.21.1
Summary: Manage Field Service Locations, Workers and Orders
Home-page: https://github.com/OCA/field-service
Author: Open Source Integrators, Odoo Community Association (OCA)
Author-email: support@odoo-community.org
License: AGPL-3
Platform: UNKNOWN
Classifier: Programming Language :: Python
Classifier: Framework :: Odoo
Classifier: Framework :: Odoo :: 12.0
Classifier: License :: OSI Approved :: GNU Affero General Public License v3
Classifier: Development Status :: 4 - Beta
Requires-Python: >=3.5
Requires-Dist: odoo12-addon-partner-fax
Requires-Dist: odoo12-addon-web-timeline
Requires-Dist: odoo (<12.1dev,>=12.0a)
